sensitivities/distributions.py
sensitivities/linear.py
sensitivities/math.py
sensitivities/stochastic.py
sensitivities-1.2.0.dist-info/licenses/LICENSE
sensitivities-1.2.0.dist-info/METADATA
sensitivities-1.2.0.dist-info/WHEEL
sensitivities-1.2.0.dist-info/top_level.txt
sensitivities-1.2.0.dist-info/RECORD
