Metadata-Version: 2.4
Name: sensitivities
Version: 1.2.0
Summary: Linear and stochastic sensitivity analysis and uncertainty propagation
Author: Luis Riegger
Author-email: lri@me.com
License: MIT
Project-URL: homepage, https://github.com/himbeles/sensitivities
Project-URL: repository, https://github.com/himbeles/sensitivities
Requires-Python: >=3.12
License-File: LICENSE
Requires-Dist: numpy
Requires-Dist: scipy
Dynamic: license-file
